AUTHORS.txt
CHANGES.rst
CLASSIFIERS.txt
LICENSE
MANIFEST.in
README.rst
REQUIREMENTS.txt
setup.py
piwigotools/__init__.py
piwigotools/__init__.pyc
piwigotools/interface.py
piwigotools/interface.pyc
piwigotools/main.py
piwigotools.egg-info/PKG-INFO
piwigotools.egg-info/SOURCES.txt
piwigotools.egg-info/dependency_links.txt
piwigotools.egg-info/entry_points.txt
piwigotools.egg-info/requires.txt
piwigotools.egg-info/top_level.txt
piwigotools/__pycache__/__init__.cpython-34.pyc
piwigotools/__pycache__/interface.cpython-34.pyc
piwigotools/progressbar/__init__.py
piwigotools/progressbar/__init__.pyc
piwigotools/progressbar/compat.py
piwigotools/progressbar/compat.pyc
piwigotools/progressbar/progressbar.py
piwigotools/progressbar/progressbar.pyc
piwigotools/progressbar/widgets.py
piwigotools/progressbar/widgets.pyc
piwigotools/progressbar/__pycache__/__init__.cpython-34.pyc
piwigotools/progressbar/__pycache__/compat.cpython-34.pyc
piwigotools/progressbar/__pycache__/progressbar.cpython-34.pyc
piwigotools/progressbar/__pycache__/widgets.cpython-34.pyc